{
  "_": {
    "postman_id": "963c901a-ab96-4cd0-a116-98252aeb3383"
  },
  "item": [
    {
      "id": "e527395f-8941-4607-b68b-59ae39053ec3",
      "name": "Authentication",
      "description": {
        "content": "",
        "type": "text/plain"
      },
      "item": [
        {
          "id": "da45d073-411d-4a9d-9364-da133c772db9",
          "name": "Public Token Exchange",
          "request": {
            "name": "Public Token Exchange",
            "description": {
              "content": "Exchange the `publicToken` returned by our hosted authentication flow for a long lived connection token that will be used when requesting data from a customer's TSP.",
              "type": "text/plain"
            },
            "url": {
              "path": [
                "public-token",
                "exchange"
              ],
              "host": [
                "{{baseUrl}}"
              ],
              "query": [],
              "variable": []
            },
            "header": [
              {
                "key": "Content-Type",
                "value": "application/json"
              },
              {
                "key": "Accept",
                "value": "application/json"
              }
            ],
            "method": "POST",
            "body": {
              "mode": "raw",
              "raw": "{\n    \"publicToken\": \"INSERT_PUBLIC_TOKEN\"\n}",
              "options": {
                "raw": {
                  "language": "json"
                }
              }
            }
          },
          "response": [],
          "event": [
            {
              "listen": "test",
              "script": {
                "id": "406be25f-c2f3-44e5-97f9-7c307fbb9645",
                "type": "text/javascript",
                "exec": [
                  "// Set response object as internal variable\nlet jsonData = {};\ntry {jsonData = pm.response.json();}catch(e){}\n",
                  "// Set property value as variable\nconst _resToken = jsonData?.token;\n",
                  "// pm.collectionVariables - Set connectionToken as variable for jsonData.token\nif (_resToken !== undefined) {\n   pm.collectionVariables.set(\"connectionToken\", jsonData.token);\n   console.log(\"- use {{connectionToken}} as collection variable for value\",jsonData.token);\n} else {\n   console.log('INFO - Unable to assign variable {{connectionToken}}, as jsonData.token is undefined.');\n};\n"
                ]
              }
            }
          ],
          "protocolProfileBehavior": {
            "disableBodyPruning": true
          }
        }
      ],
      "event": []
    },
    {
      "id": "e20bf48a-723b-4b20-a9ac-20f6d3ead5a7",
      "name": "Connections",
      "description": {
        "content": "",
        "type": "text/plain"
      },
      "item": [
        {
          "id": "79b23a75-a62d-4d87-b5c4-0dfa1e060e15",
          "name": "List All Connections",
          "request": {
            "name": "List All Connections",
            "description": {
              "content": "List all of the connections you have for your application. Connections represent the authenticated access you have to your customer's TSP data.",
              "type": "text/plain"
            },
            "url": {
              "path": [
                "connections"
              ],
              "host": [
                "{{baseUrl}}"
              ],
              "query": [
                {
                  "disabled": true,
                  "description": {
                    "content": "Pagination cursor to start requests from",
                    "type": "text/plain"
                  },
                  "key": "cursor",
                  "value": "{{nextCursor}}"
                },
                {
                  "disabled": true,
                  "description": {
                    "content": "The maximum number of results to return in a page.",
                    "type": "text/plain"
                  },
                  "key": "limit",
                  "value": "1"
                },
                {
                  "disabled": true,
                  "key": "externalId",
                  "value": "123"
                },
                {
                  "disabled": true,
                  "key": "dotNumber",
                  "value": "123"
                }
              ],
              "variable": []
            },
            "header": [
              {
                "key": "Accept",
                "value": "application/json"
              }
            ],
            "method": "GET"
          },
          "response": [],
          "event": [
            {
              "listen": "test",
              "script": {
                "id": "9b446ba0-5269-4757-99f5-0e5682c0b3bd",
                "type": "text/javascript",
                "exec": [
                  "// Set response object as internal variable\nlet jsonData = {};\ntry {jsonData = pm.response.json();}catch(e){}\n",
                  "// Set property value as variable\nconst _resNext = jsonData?.next;\n",
                  "// pm.collectionVariables - Set nextCursor as variable for jsonData.next\nif (_resNext !== undefined) {\n   pm.collectionVariables.set(\"nextCursor\", jsonData.next);\n   console.log(\"- use {{nextCursor}} as collection variable for value\",jsonData.next);\n} else {\n   console.log('INFO - Unable to assign variable {{nextCursor}}, as jsonData.next is undefined.');\n};\n"
                ]
              }
            }
          ],
          "protocolProfileBehavior": {
            "disableBodyPruning": true
          }
        },
        {
          "id": "8b66b4d0-0a01-4a96-ba92-5fe73375609e",
          "name": "Create Connection",
          "request": {
            "name": "Create Connection",
            "description": {
              "content": "Create a new connection via API. This endpoint can be used to provide a completely custom connection creation experience for your customers.\n\nFor most use cases we recommend using the [Link UI](./rhuaxk9205cn8-link-component) to create connections.",
              "type": "text/plain"
            },
            "url": {
              "path": [
                "connections"
              ],
              "host": [
                "{{baseUrl}}"
              ],
              "query": [],
              "variable": []
            },
            "header": [
              {
                "key": "Content-Type",
                "value": "application/json"
              },
              {
                "key": "Accept",
                "value": "application/json"
              }
            ],
            "method": "POST",
            "body": {
              "mode": "raw",
              "raw": "{\n  \"provider\": \"geotab\",\n  \"credentials\": {\n    \"username\": \"ex\",\n    \"password\": \"in Ut do minim\",\n    \"database\": \"aute Lorem in labore\"\n  },\n  \"company\": {\n    \"name\": \"dolor\",\n    \"dotNumbers\": [\n      \"in velit sint ea\",\n      \"quis ut esse incididunt do\"\n    ]\n  },\n  \"externalId\": \"cillum ad aute\",\n  \"syncMode\": \"automatic\",\n  \"backfill\": {\n    \"startFrom\": \"2021-01-06T03:24:53.000Z\",\n    \"days\": 6253099.659807488\n  }\n}",
              "options": {
                "raw": {
                  "language": "json"
                }
              }
            }
          },
          "response": [],
          "event": [],
          "protocolProfileBehavior": {
            "disableBodyPruning": true
          }
        },
        {
          "id": "abb90881-59d3-483a-9e35-4fc0220e7add",
          "name": "Get Current Connection",
          "request": {
            "name": "Get Current Connection",
            "description": {
              "content": "Get the details of the current active connection. The current connection is derived from the provided connection token.",
              "type": "text/plain"
            },
            "url": {
              "path": [
                "connections",
                "current"
              ],
              "host": [
                "{{baseUrl}}"
              ],
              "query": [],
              "variable": []
            },
            "header": [
              {
                "disabled": false,
                "description": {
                  "content": "(Required) The token returned when a user authenticated their account. This authorizes access to a specific account.",
                  "type": "text/plain"
                },
                "key": "Connection-Token",
                "value": "{{connectionToken}}"
              },
              {
                "key": "Accept",
                "value": "application/json"
              }
            ],
            "method": "GET"
          },
          "response": [],
          "event": [
            {
              "listen": "test",
              "script": {
                "id": "40d1315e-b1c9-4e1f-8713-bd85fe4db54b",
                "type": "text/javascript",
                "exec": [
                  "// Set response object as internal variable\nlet jsonData = {};\ntry {jsonData = pm.response.json();}catch(e){}\n",
                  "// Set property value as variable\nconst _resNext = jsonData?.next;\n",
                  "// pm.collectionVariables - Set nextCursor as variable for jsonData.next\nif (_resNext !== undefined) {\n   pm.collectionVariables.set(\"nextCursor\", jsonData.next);\n   console.log(\"- use {{nextCursor}} as collection variable for value\",jsonData.next);\n} else {\n   console.log('INFO - Unable to assign variable {{nextCursor}}, as jsonData.next is undefined.');\n};\n"
                ]
              }
            }
          ],
          "protocolProfileBehavior": {
            "disableBodyPruning": true
          }
        },
        {
          "id": "7fc8c413-5519-4c00-800e-1adcd3aecc9c",
          "name": "Update Current Connection",
          "request": {
            "name": "Update Current Connection",
            "description": {
              "content": "Update the details of the current active connection. The current connection is derived from the provided connection token.",
              "type": "text/plain"
            },
            "url": {
              "path": [
                "connections",
                "current"
              ],
              "host": [
                "{{baseUrl}}"
              ],
              "query": [],
              "variable": []
            },
            "header": [
              {
                "disabled": false,
                "description": {
                  "content": "(Required) The token returned when a user authenticated their account. This authorizes access to a specific account.",
                  "type": "text/plain"
                },
                "key": "Connection-Token",
                "value": "{{connectionToken}}"
              },
              {
                "key": "Content-Type",
                "value": "application/json"
              },
              {
                "key": "Accept",
                "value": "application/json"
              }
            ],
            "method": "PATCH",
            "body": {
              "mode": "raw",
              "raw": "{\n  \"status\": \"laboris consequat\",\n  \"company\": {\n    \"name\": \"Acme Inc.\"\n  },\n  \"externalId\": \"id minim\",\n  \"syncMode\": \"automatic\"\n}",
              "options": {
                "raw": {
                  "language": "json"
                }
              }
            }
          },
          "response": [],
          "event": [],
          "protocolProfileBehavior": {
            "disableBodyPruning": true
          }
        }
      ],
      "event": []
    },
    {
      "id": "3a02eb56-879a-41fa-ac76-53064cf2a560",
      "name": "Data Management",
      "description": {
        "content": "",
        "type": "text/plain"
      },
      "item": [
        {
          "id": "f3093c2b-26e4-424c-8870-6223b1d46286",
          "name": "Request Sync",
          "request": {
            "name": "Request Sync",
            "description": {
              "content": "Manually request to sync the current connections data.\n\nBy default, Terminal will sync all connections where `syncMode = automatic` on a regular cadence. For customers that may not need a fleet's data to be kept up to date and want to reduce their active tracked trucks, you can set `syncMode = manual` and invoke this endpoint when you want to sync data.\n\nIf you're wondering if this is relevent to your use case then feel free to reach out and we'd be happy to assist.",
              "type": "text/plain"
            },
            "url": {
              "path": [
                "syncs"
              ],
              "host": [
                "{{baseUrl}}"
              ],
              "query": [],
              "variable": []
            },
            "header": [
              {
                "disabled": false,
                "description": {
                  "content": "(Required) The token returned when a user authenticated their account. This authorizes access to a specific account.",
                  "type": "text/plain"
                },
                "key": "Connection-Token",
                "value": "{{connectionToken}}"
              },
              {
                "key": "Content-Type",
                "value": "application/json"
              },
              {
                "key": "Accept",
                "value": "application/json"
              }
            ],
            "method": "POST",
            "body": {
              "mode": "raw",
              "raw": "{\n  \"days\": 7\n}",
              "options": {
                "raw": {
                  "language": "json"
                }
              }
            }
          },
          "response": [],
          "event": [
            {
              "listen": "test",
              "script": {
                "id": "cf146491-73d1-4acc-888e-16c468b38789",
                "type": "text/javascript",
                "exec": [
                  "// Set response object as internal variable\nlet jsonData = {};\ntry {jsonData = pm.response.json();}catch(e){}\n",
                  "// Set property value as variable\nconst _resId = jsonData?.id;\n",
                  "// pm.collectionVariables - Set syncId as variable for jsonData.id\nif (_resId !== undefined) {\n   pm.collectionVariables.set(\"syncId\", jsonData.id);\n   console.log(\"- use {{syncId}} as collection variable for value\",jsonData.id);\n} else {\n   console.log('INFO - Unable to assign variable {{syncId}}, as jsonData.id is undefined.');\n};\n"
                ]
              }
            }
          ],
          "protocolProfileBehavior": {
            "disableBodyPruning": true
          }
        },
        {
          "id": "81a0968e-474e-49df-84fa-585513995935",
          "name": "List Sync History",
          "request": {
            "name": "List Sync History",
            "description": {
              "content": "List a log of all batch sync jobs for the current connection.",
              "type": "text/plain"
            },
            "url": {
              "path": [
                "syncs"
              ],
              "host": [
                "{{baseUrl}}"
              ],
              "query": [
                {
                  "disabled": true,
                  "description": {
                    "content": "The maximum number of results to return in a page.",
                    "type": "text/plain"
                  },
                  "key": "limit",
                  "value": "1"
                },
                {
                  "disabled": true,
                  "description": {
                    "content": "Pagination cursor to start requests from",
                    "type": "text/plain"
                  },
                  "key": "cursor",
                  "value": "{{nextCursor}}"
                },
                {
                  "disabled": true,
                  "key": "status",
                  "value": "in_progress"
                }
              ],
              "variable": []
            },
            "header": [
              {
                "disabled": false,
                "description": {
                  "content": "(Required) The token returned when a user authenticated their account. This authorizes access to a specific account.",
                  "type": "text/plain"
                },
                "key": "Connection-Token",
                "value": "{{connectionToken}}"
              },
              {
                "key": "Accept",
                "value": "application/json"
              }
            ],
            "method": "GET"
          },
          "response": [],
          "event": [
            {
              "listen": "test",
              "script": {
                "id": "f97426a9-c534-4d69-847d-e7a1dc02f2b6",
                "type": "text/javascript",
                "exec": [
                  "// Set response object as internal variable\nlet jsonData = {};\ntry {jsonData = pm.response.json();}catch(e){}\n",
                  "// Set property value as variable\nconst _resNext = jsonData?.next;\n",
                  "// pm.collectionVariables - Set nextCursor as variable for jsonData.next\nif (_resNext !== undefined) {\n   pm.collectionVariables.set(\"nextCursor\", jsonData.next);\n   console.log(\"- use {{nextCursor}} as collection variable for value\",jsonData.next);\n} else {\n   console.log('INFO - Unable to assign variable {{nextCursor}}, as jsonData.next is undefined.');\n};\n",
                  "// Set property value as variable\nconst _resResults0Id = jsonData?.results?.[0]?.id;\n",
                  "// pm.collectionVariables - Set syncId as variable for jsonData.results[0].id\nif (_resResults0Id !== undefined) {\n   pm.collectionVariables.set(\"syncId\", jsonData.results[0].id);\n   console.log(\"- use {{syncId}} as collection variable for value\",jsonData.results[0].id);\n} else {\n   console.log('INFO - Unable to assign variable {{syncId}}, as jsonData.results[0].id is undefined.');\n};\n"
                ]
              }
            }
          ],
          "protocolProfileBehavior": {
            "disableBodyPruning": true
          }
        },
        {
          "id": "7c96ff05-ec97-4d21-959d-6294a3a3b04b",
          "name": "Get Sync Job Status",
          "request": {
            "name": "Get Sync Job Status",
            "description": {
              "content": "Get the status of a sync job by ID.",
              "type": "text/plain"
            },
            "url": {
              "path": [
                "syncs",
                ":id"
              ],
              "host": [
                "{{baseUrl}}"
              ],
              "query": [],
              "variable": [
                {
                  "disabled": false,
                  "description": {
                    "content": "(Required) ",
                    "type": "text/plain"
                  },
                  "type": "string",
                  "value": "{{syncId}}",
                  "key": "id"
                }
              ]
            },
            "header": [
              {
                "disabled": false,
                "description": {
                  "content": "(Required) The token returned when a user authenticated their account. This authorizes access to a specific account.",
                  "type": "text/plain"
                },
                "key": "Connection-Token",
                "value": "{{connectionToken}}"
              },
              {
                "key": "Accept",
                "value": "application/json"
              }
            ],
            "method": "GET"
          },
          "response": [],
          "event": [
            {
              "listen": "test",
              "script": {
                "id": "5e272ad9-cd46-402f-ac24-d9915bae3bb8",
                "type": "text/javascript",
                "exec": [
                  "// Set response object as internal variable\nlet jsonData = {};\ntry {jsonData = pm.response.json();}catch(e){}\n",
                  "// Set property value as variable\nconst _resNext = jsonData?.next;\n",
                  "// pm.collectionVariables - Set nextCursor as variable for jsonData.next\nif (_resNext !== undefined) {\n   pm.collectionVariables.set(\"nextCursor\", jsonData.next);\n   console.log(\"- use {{nextCursor}} as collection variable for value\",jsonData.next);\n} else {\n   console.log('INFO - Unable to assign variable {{nextCursor}}, as jsonData.next is undefined.');\n};\n"
                ]
              }
            }
          ],
          "protocolProfileBehavior": {
            "disableBodyPruning": true
          }
        },
        {
          "id": "bc9ef9d1-114d-482f-ad3f-53c555d659d5",
          "name": "Passthrough",
          "request": {
            "name": "Passthrough",
            "description": {
              "content": "Make an authenticated request to the underlying telematics provider. \n\nThis endpoint helps ensure that you are never limited by Terminal. You can use passthrough requests to access capabilities that may be limited to a specific TSP or not yet in the normalized model.\n\nOur team is here an ready to support custom use cases that may need `/passthrough`",
              "type": "text/plain"
            },
            "url": {
              "path": [
                "passthrough"
              ],
              "host": [
                "{{baseUrl}}"
              ],
              "query": [],
              "variable": []
            },
            "header": [
              {
                "disabled": false,
                "description": {
                  "content": "(Required) The token returned when a user authenticated their account. This authorizes access to a specific account.",
                  "type": "text/plain"
                },
                "key": "Connection-Token",
                "value": "{{connectionToken}}"
              },
              {
                "key": "Content-Type",
                "value": "application/json"
              },
              {
                "key": "Accept",
                "value": "application/json"
              }
            ],
            "method": "POST",
            "body": {
              "mode": "raw",
              "raw": "{\n  \"method\": \"POST\",\n  \"path\": \"/reports\",\n  \"headers\": {},\n  \"body\": \"{\\\"reportId\\\":\\\"1234\\\"}\"\n}",
              "options": {
                "raw": {
                  "language": "json"
                }
              }
            }
          },
          "response": [],
          "event": [],
          "protocolProfileBehavior": {
            "disableBodyPruning": true
          }
        }
      ],
      "event": []
    },
    {
      "id": "7f6d29bf-dbb2-4ed1-b593-8b96b0d0183c",
      "name": "Drivers",
      "description": {
        "content": "",
        "type": "text/plain"
      },
      "item": [
        {
          "id": "ab03a44e-69e7-48c9-9597-dc6a3f78ab7b",
          "name": "List Drivers",
          "request": {
            "name": "List Drivers",
            "description": {
              "content": "List all of the drivers in the connected account",
              "type": "text/plain"
            },
            "url": {
              "path": [
                "drivers"
              ],
              "host": [
                "{{baseUrl}}"
              ],
              "query": [
                {
                  "disabled": true,
                  "description": {
                    "content": "Pagination cursor to start requests from",
                    "type": "text/plain"
                  },
                  "key": "cursor",
                  "value": "{{nextCursor}}"
                },
                {
                  "disabled": true,
                  "description": {
                    "content": "The maximum number of results to return in a page.",
                    "type": "text/plain"
                  },
                  "key": "limit",
                  "value": "1"
                },
                {
                  "disabled": true,
                  "description": {
                    "content": "Only include records that were last modified after a provided date.",
                    "type": "text/plain"
                  },
                  "key": "modifiedAfter",
                  "value": "2021-01-06T03:24:53.000Z"
                },
                {
                  "disabled": true,
                  "description": {
                    "content": "Only include records that were last modified before a provided date.",
                    "type": "text/plain"
                  },
                  "key": "modifiedBefore",
                  "value": "2021-01-06T03:24:53.000Z"
                },
                {
                  "disabled": true,
                  "description": {
                    "content": "Include raw responses used to normalize model. Used for debugging or accessing unique properties that are not unified.",
                    "type": "text/plain"
                  },
                  "key": "raw",
                  "value": "true"
                },
                {
                  "disabled": true,
                  "description": {
                    "content": "Expand resources in the returned response",
                    "type": "text/plain"
                  },
                  "key": "expand",
                  "value": "vehicle"
                }
              ],
              "variable": []
            },
            "header": [
              {
                "disabled": false,
                "description": {
                  "content": "(Required) The token returned when a user authenticated their account. This authorizes access to a specific account.",
                  "type": "text/plain"
                },
                "key": "Connection-Token",
                "value": "{{connectionToken}}"
              },
              {
                "key": "Accept",
                "value": "application/json"
              }
            ],
            "method": "GET"
          },
          "response": [],
          "event": [
            {
              "listen": "test",
              "script": {
                "id": "301930bb-ef24-4150-aeb8-92b1e032d7f4",
                "type": "text/javascript",
                "exec": [
                  "// Set response object as internal variable\nlet jsonData = {};\ntry {jsonData = pm.response.json();}catch(e){}\n",
                  "// Set property value as variable\nconst _resNext = jsonData?.next;\n",
                  "// pm.collectionVariables - Set nextCursor as variable for jsonData.next\nif (_resNext !== undefined) {\n   pm.collectionVariables.set(\"nextCursor\", jsonData.next);\n   console.log(\"- use {{nextCursor}} as collection variable for value\",jsonData.next);\n} else {\n   console.log('INFO - Unable to assign variable {{nextCursor}}, as jsonData.next is undefined.');\n};\n",
                  "// Set property value as variable\nconst _resResults0Id = jsonData?.results?.[0]?.id;\n",
                  "// pm.collectionVariables - Set driverId as variable for jsonData.results[0].id\nif (_resResults0Id !== undefined) {\n   pm.collectionVariables.set(\"driverId\", jsonData.results[0].id);\n   console.log(\"- use {{driverId}} as collection variable for value\",jsonData.results[0].id);\n} else {\n   console.log('INFO - Unable to assign variable {{driverId}}, as jsonData.results[0].id is undefined.');\n};\n"
                ]
              }
            }
          ],
          "protocolProfileBehavior": {
            "disableBodyPruning": true
          }
        },
        {
          "id": "77375a17-2fec-4e65-906d-aa60687534da",
          "name": "Get Driver",
          "request": {
            "name": "Get Driver",
            "description": {
              "content": "Get the details of a specific driver",
              "type": "text/plain"
            },
            "url": {
              "path": [
                "drivers",
                ":id"
              ],
              "host": [
                "{{baseUrl}}"
              ],
              "query": [
                {
                  "disabled": true,
                  "description": {
                    "content": "Include raw responses used to normalize model. Used for debugging or accessing unique properties that are not unified.",
                    "type": "text/plain"
                  },
                  "key": "raw",
                  "value": "true"
                },
                {
                  "disabled": true,
                  "description": {
                    "content": "Expand resources in the returned response",
                    "type": "text/plain"
                  },
                  "key": "expand",
                  "value": "vehicle"
                }
              ],
              "variable": [
                {
                  "disabled": false,
                  "description": {
                    "content": "(Required) ",
                    "type": "text/plain"
                  },
                  "type": "string",
                  "value": "{{driverId}}",
                  "key": "id"
                }
              ]
            },
            "header": [
              {
                "disabled": false,
                "description": {
                  "content": "(Required) The token returned when a user authenticated their account. This authorizes access to a specific account.",
                  "type": "text/plain"
                },
                "key": "Connection-Token",
                "value": "{{connectionToken}}"
              },
              {
                "key": "Accept",
                "value": "application/json"
              }
            ],
            "method": "GET"
          },
          "response": [],
          "event": [
            {
              "listen": "test",
              "script": {
                "id": "4f5e1889-7741-4817-a38e-193dc5e8a391",
                "type": "text/javascript",
                "exec": [
                  "// Set response object as internal variable\nlet jsonData = {};\ntry {jsonData = pm.response.json();}catch(e){}\n",
                  "// Set property value as variable\nconst _resNext = jsonData?.next;\n",
                  "// pm.collectionVariables - Set nextCursor as variable for jsonData.next\nif (_resNext !== undefined) {\n   pm.collectionVariables.set(\"nextCursor\", jsonData.next);\n   console.log(\"- use {{nextCursor}} as collection variable for value\",jsonData.next);\n} else {\n   console.log('INFO - Unable to assign variable {{nextCursor}}, as jsonData.next is undefined.');\n};\n"
                ]
              }
            }
          ],
          "protocolProfileBehavior": {
            "disableBodyPruning": true
          }
        }
      ],
      "event": []
    },
    {
      "id": "4970773d-503c-44fd-9ab8-ae0043f49e5c",
      "name": "Groups",
      "description": {
        "content": "",
        "type": "text/plain"
      },
      "item": [
        {
          "id": "7ccf4d31-8828-4bf6-9354-b3f78a466e5f",
          "name": "List Groups",
          "request": {
            "name": "List Groups",
            "description": {
              "type": "text/plain"
            },
            "url": {
              "path": [
                "groups"
              ],
              "host": [
                "{{baseUrl}}"
              ],
              "query": [
                {
                  "disabled": true,
                  "description": {
                    "content": "The maximum number of results to return in a page.",
                    "type": "text/plain"
                  },
                  "key": "limit",
                  "value": "1"
                },
                {
                  "disabled": true,
                  "description": {
                    "content": "Pagination cursor to start requests from",
                    "type": "text/plain"
                  },
                  "key": "cursor",
                  "value": "{{nextCursor}}"
                },
                {
                  "disabled": true,
                  "description": {
                    "content": "Expand resources in the returned response",
                    "type": "text/plain"
                  },
                  "key": "expand",
                  "value": "vehicle"
                },
                {
                  "disabled": true,
                  "description": {
                    "content": "Include raw responses used to normalize model. Used for debugging or accessing unique properties that are not unified.",
                    "type": "text/plain"
                  },
                  "key": "raw",
                  "value": "true"
                },
                {
                  "disabled": true,
                  "description": {
                    "content": "Only include records that were last modified after a provided date.",
                    "type": "text/plain"
                  },
                  "key": "modifiedAfter",
                  "value": "2021-01-06T03:24:53.000Z"
                },
                {
                  "disabled": true,
                  "description": {
                    "content": "Only include records that were last modified before a provided date.",
                    "type": "text/plain"
                  },
                  "key": "modifiedBefore",
                  "value": "2021-01-06T03:24:53.000Z"
                }
              ],
              "variable": []
            },
            "header": [
              {
                "disabled": false,
                "description": {
                  "content": "(Required) The token returned when a user authenticated their account. This authorizes access to a specific account.",
                  "type": "text/plain"
                },
                "key": "Connection-Token",
                "value": "{{connectionToken}}"
              },
              {
                "key": "Accept",
                "value": "application/json"
              }
            ],
            "method": "GET"
          },
          "response": [],
          "event": [
            {
              "listen": "test",
              "script": {
                "id": "eaa347d4-f541-4cef-a4a8-956b5cd1c056",
                "type": "text/javascript",
                "exec": [
                  "// Set response object as internal variable\nlet jsonData = {};\ntry {jsonData = pm.response.json();}catch(e){}\n",
                  "// Set property value as variable\nconst _resNext = jsonData?.next;\n",
                  "// pm.collectionVariables - Set nextCursor as variable for jsonData.next\nif (_resNext !== undefined) {\n   pm.collectionVariables.set(\"nextCursor\", jsonData.next);\n   console.log(\"- use {{nextCursor}} as collection variable for value\",jsonData.next);\n} else {\n   console.log('INFO - Unable to assign variable {{nextCursor}}, as jsonData.next is undefined.');\n};\n"
                ]
              }
            }
          ],
          "protocolProfileBehavior": {
            "disableBodyPruning": true
          }
        }
      ],
      "event": []
    },
    {
      "id": "15e2def7-e76e-4663-9b93-c5e4c0dee5d8",
      "name": "Hours of Service",
      "description": {
        "content": "",
        "type": "text/plain"
      },
      "item": [
        {
          "id": "eff1977e-d8da-4c69-b24e-2168d20032d0",
          "name": "Available Time for Drivers",
          "request": {
            "name": "Available Time for Drivers",
            "description": {
              "content": "List available time for the driver. This endpoint provides live access to the driver's available time. Different than most endpoints, this endpoint calls the provider's API in real time to get the latest available time for the driver. This endpoint is useful for building real time applications that need to know the driver's available time.",
              "type": "text/plain"
            },
            "url": {
              "path": [
                "hos",
                "available-time"
              ],
              "host": [
                "{{baseUrl}}"
              ],
              "query": [
                {
                  "disabled": true,
                  "description": {
                    "content": "Pagination cursor to start requests from",
                    "type": "text/plain"
                  },
                  "key": "cursor",
                  "value": "{{nextCursor}}"
                },
                {
                  "disabled": true,
                  "description": {
                    "content": "The maximum number of results to return in a page.",
                    "type": "text/plain"
                  },
                  "key": "limit",
                  "value": "1"
                },
                {
                  "disabled": true,
                  "description": {
                    "content": "Comma separated list of driver IDs to filter for",
                    "type": "text/plain"
                  },
                  "key": "driverIds",
                  "value": "{{driverId}}"
                },
                {
                  "disabled": true,
                  "description": {
                    "content": "Expand resources in the returned response",
                    "type": "text/plain"
                  },
                  "key": "expand",
                  "value": "vehicle"
                },
                {
                  "disabled": true,
                  "description": {
                    "content": "Include raw responses used to normalize model. Used for debugging or accessing unique properties that are not unified.",
                    "type": "text/plain"
                  },
                  "key": "raw",
                  "value": "true"
                }
              ],
              "variable": []
            },
            "header": [
              {
                "disabled": false,
                "description": {
                  "content": "(Required) The token returned when a user authenticated their account. This authorizes access to a specific account.",
                  "type": "text/plain"
                },
                "key": "Connection-Token",
                "value": "{{connectionToken}}"
              },
              {
                "key": "Accept",
                "value": "application/json"
              }
            ],
            "method": "GET"
          },
          "response": [],
          "event": [
            {
              "listen": "test",
              "script": {
                "id": "597d78cb-2a71-4e30-ad4b-1ed94a462325",
                "type": "text/javascript",
                "exec": [
                  "// Set response object as internal variable\nlet jsonData = {};\ntry {jsonData = pm.response.json();}catch(e){}\n",
                  "// Set property value as variable\nconst _resNext = jsonData?.next;\n",
                  "// pm.collectionVariables - Set nextCursor as variable for jsonData.next\nif (_resNext !== undefined) {\n   pm.collectionVariables.set(\"nextCursor\", jsonData.next);\n   console.log(\"- use {{nextCursor}} as collection variable for value\",jsonData.next);\n} else {\n   console.log('INFO - Unable to assign variable {{nextCursor}}, as jsonData.next is undefined.');\n};\n"
                ]
              }
            }
          ],
          "protocolProfileBehavior": {
            "disableBodyPruning": true
          }
        },
        {
          "id": "046e0b75-40d2-4a08-b87c-c6128cfb30b6",
          "name": "List HOS Logs",
          "request": {
            "name": "List HOS Logs",
            "description": {
              "content": "List all hours of service logs. Currently, HOS logs are tracked as the distinct changes in duty status. In the future we will be offering endpoints to expose current HOS status and historical daily summaries.",
              "type": "text/plain"
            },
            "url": {
              "path": [
                "hos",
                "logs"
              ],
              "host": [
                "{{baseUrl}}"
              ],
              "query": [
                {
                  "disabled": true,
                  "description": {
                    "content": "Pagination cursor to start requests from",
                    "type": "text/plain"
                  },
                  "key": "cursor",
                  "value": "{{nextCursor}}"
                },
                {
                  "disabled": true,
                  "description": {
                    "content": "The maximum number of results to return in a page.",
                    "type": "text/plain"
                  },
                  "key": "limit",
                  "value": "1"
                },
                {
                  "disabled": true,
                  "description": {
                    "content": "Only include records of statuses that started after a provided date.",
                    "type": "text/plain"
                  },
                  "key": "startedAfter",
                  "value": "2021-01-06T03:24:53.000Z"
                },
                {
                  "disabled": true,
                  "description": {
                    "content": "Only include records of statuses that started before a provided date.",
                    "type": "text/plain"
                  },
                  "key": "startedBefore",
                  "value": "2021-01-06T03:24:53.000Z"
                },
                {
                  "disabled": true,
                  "description": {
                    "content": "Only include records that were last modified after a provided date.",
                    "type": "text/plain"
                  },
                  "key": "modifiedAfter",
                  "value": "2021-01-06T03:24:53.000Z"
                },
                {
                  "disabled": true,
                  "description": {
                    "content": "Only include records that were last modified before a provided date.",
                    "type": "text/plain"
                  },
                  "key": "modifiedBefore",
                  "value": "2021-01-06T03:24:53.000Z"
                },
                {
                  "disabled": true,
                  "description": {
                    "content": "Comma separated list of driver IDs to filter for",
                    "type": "text/plain"
                  },
                  "key": "driverIds",
                  "value": "{{driverId}}"
                },
                {
                  "disabled": true,
                  "description": {
                    "content": "Expand resources in the returned response",
                    "type": "text/plain"
                  },
                  "key": "expand",
                  "value": "vehicle"
                },
                {
                  "disabled": true,
                  "description": {
                    "content": "Include raw responses used to normalize model. Used for debugging or accessing unique properties that are not unified.",
                    "type": "text/plain"
                  },
                  "key": "raw",
                  "value": "true"
                }
              ],
              "variable": []
            },
            "header": [
              {
                "disabled": false,
                "description": {
                  "content": "(Required) The token returned when a user authenticated their account. This authorizes access to a specific account.",
                  "type": "text/plain"
                },
                "key": "Connection-Token",
                "value": "{{connectionToken}}"
              },
              {
                "key": "Accept",
                "value": "application/json"
              }
            ],
            "method": "GET"
          },
          "response": [],
          "event": [
            {
              "listen": "test",
              "script": {
                "id": "80a76c2c-062e-4dba-b311-b9ada539f429",
                "type": "text/javascript",
                "exec": [
                  "// Set response object as internal variable\nlet jsonData = {};\ntry {jsonData = pm.response.json();}catch(e){}\n",
                  "// Set property value as variable\nconst _resNext = jsonData?.next;\n",
                  "// pm.collectionVariables - Set nextCursor as variable for jsonData.next\nif (_resNext !== undefined) {\n   pm.collectionVariables.set(\"nextCursor\", jsonData.next);\n   console.log(\"- use {{nextCursor}} as collection variable for value\",jsonData.next);\n} else {\n   console.log('INFO - Unable to assign variable {{nextCursor}}, as jsonData.next is undefined.');\n};\n"
                ]
              }
            }
          ],
          "protocolProfileBehavior": {
            "disableBodyPruning": true
          }
        },
        {
          "id": "de88d629-b17e-4262-86b0-abd356020adb",
          "name": "List HOS Daily Logs",
          "request": {
            "name": "List HOS Daily Logs",
            "description": {
              "content": "List daily summary of hours of service. Each daily log represents the time a driver spent in each duty status for a given day.",
              "type": "text/plain"
            },
            "url": {
              "path": [
                "hos",
                "daily-logs"
              ],
              "host": [
                "{{baseUrl}}"
              ],
              "query": [
                {
                  "disabled": true,
                  "description": {
                    "content": "Pagination cursor to start requests from",
                    "type": "text/plain"
                  },
                  "key": "cursor",
                  "value": "{{nextCursor}}"
                },
                {
                  "disabled": true,
                  "description": {
                    "content": "The maximum number of results to return in a page.",
                    "type": "text/plain"
                  },
                  "key": "limit",
                  "value": "1"
                },
                {
                  "disabled": false,
                  "description": {
                    "content": "Only include daily logs from on or after a specific date",
                    "type": "text/plain"
                  },
                  "key": "startDate",
                  "value": "2019-08-30"
                },
                {
                  "disabled": false,
                  "description": {
                    "content": "Only include daily logs from on or before a specific date",
                    "type": "text/plain"
                  },
                  "key": "endDate",
                  "value": "2019-08-30"
                },
                {
                  "disabled": true,
                  "description": {
                    "content": "Only include records that were last modified after a provided date.",
                    "type": "text/plain"
                  },
                  "key": "modifiedAfter",
                  "value": "2021-01-06T03:24:53.000Z"
                },
                {
                  "disabled": true,
                  "description": {
                    "content": "Only include records that were last modified before a provided date.",
                    "type": "text/plain"
                  },
                  "key": "modifiedBefore",
                  "value": "2021-01-06T03:24:53.000Z"
                },
                {
                  "disabled": true,
                  "description": {
                    "content": "Comma separated list of driver IDs to filter for",
                    "type": "text/plain"
                  },
                  "key": "driverIds",
                  "value": "{{driverId}}"
                },
                {
                  "disabled": true,
                  "description": {
                    "content": "Include raw responses used to normalize model. Used for debugging or accessing unique properties that are not unified.",
                    "type": "text/plain"
                  },
                  "key": "raw",
                  "value": "true"
                },
                {
                  "disabled": true,
                  "description": {
                    "content": "Expand resources in the returned response",
                    "type": "text/plain"
                  },
                  "key": "expand",
                  "value": "vehicle"
                }
              ],
              "variable": []
            },
            "header": [
              {
                "disabled": false,
                "description": {
                  "content": "(Required) The token returned when a user authenticated their account. This authorizes access to a specific account.",
                  "type": "text/plain"
                },
                "key": "Connection-Token",
                "value": "{{connectionToken}}"
              },
              {
                "key": "Accept",
                "value": "application/json"
              }
            ],
            "method": "GET"
          },
          "response": [],
          "event": [
            {
              "listen": "test",
              "script": {
                "id": "fe5515a0-688f-456b-b5d4-74c77c2d45a2",
                "type": "text/javascript",
                "exec": [
                  "// Set response object as internal variable\nlet jsonData = {};\ntry {jsonData = pm.response.json();}catch(e){}\n",
                  "// Set property value as variable\nconst _resNext = jsonData?.next;\n",
                  "// pm.collectionVariables - Set nextCursor as variable for jsonData.next\nif (_resNext !== undefined) {\n   pm.collectionVariables.set(\"nextCursor\", jsonData.next);\n   console.log(\"- use {{nextCursor}} as collection variable for value\",jsonData.next);\n} else {\n   console.log('INFO - Unable to assign variable {{nextCursor}}, as jsonData.next is undefined.');\n};\n"
                ]
              }
            }
          ],
          "protocolProfileBehavior": {
            "disableBodyPruning": true
          }
        }
      ],
      "event": []
    },
    {
      "id": "f3b4ed93-195c-489a-8e45-4023012ebeeb",
      "name": "Safety",
      "description": {
        "content": "",
        "type": "text/plain"
      },
      "item": [
        {
          "id": "ebd9620e-3389-4a0a-9ef3-39018fc66170",
          "name": "List Safety Events",
          "request": {
            "name": "List Safety Events",
            "description": {
              "content": "List all safety events detected by the provider.",
              "type": "text/plain"
            },
            "url": {
              "path": [
                "safety",
                "events"
              ],
              "host": [
                "{{baseUrl}}"
              ],
              "query": [
                {
                  "disabled": true,
                  "description": {
                    "content": "Pagination cursor to start requests from",
                    "type": "text/plain"
                  },
                  "key": "cursor",
                  "value": "{{nextCursor}}"
                },
                {
                  "disabled": true,
                  "description": {
                    "content": "The maximum number of results to return in a page.",
                    "type": "text/plain"
                  },
                  "key": "limit",
                  "value": "1"
                },
                {
                  "disabled": true,
                  "description": {
                    "content": "Only include records that were last modified after a provided date.",
                    "type": "text/plain"
                  },
                  "key": "modifiedAfter",
                  "value": "2021-01-06T03:24:53.000Z"
                },
                {
                  "disabled": true,
                  "description": {
                    "content": "Only include records that were last modified before a provided date.",
                    "type": "text/plain"
                  },
                  "key": "modifiedBefore",
                  "value": "2021-01-06T03:24:53.000Z"
                },
                {
                  "disabled": true,
                  "description": {
                    "content": "Only include records of statuses that started after a provided date.",
                    "type": "text/plain"
                  },
                  "key": "startedAfter",
                  "value": "2021-01-06T03:24:53.000Z"
                },
                {
                  "disabled": true,
                  "description": {
                    "content": "Only include records of statuses that started before a provided date.",
                    "type": "text/plain"
                  },
                  "key": "startedBefore",
                  "value": "2021-01-06T03:24:53.000Z"
                },
                {
                  "disabled": true,
                  "description": {
                    "content": "Comma separated list of driver IDs to filter for",
                    "type": "text/plain"
                  },
                  "key": "driverIds",
                  "value": "{{driverId}}"
                },
                {
                  "disabled": true,
                  "description": {
                    "content": "Comma separated list of vehicle IDs to filter for",
                    "type": "text/plain"
                  },
                  "key": "vehicleIds",
                  "value": "{{vehicleId}}"
                },
                {
                  "disabled": true,
                  "description": {
                    "content": "Expand resources in the returned response",
                    "type": "text/plain"
                  },
                  "key": "expand",
                  "value": "vehicle"
                },
                {
                  "disabled": true,
                  "description": {
                    "content": "Include raw responses used to normalize model. Used for debugging or accessing unique properties that are not unified.",
                    "type": "text/plain"
                  },
                  "key": "raw",
                  "value": "true"
                }
              ],
              "variable": []
            },
            "header": [
              {
                "disabled": false,
                "description": {
                  "content": "(Required) The token returned when a user authenticated their account. This authorizes access to a specific account.",
                  "type": "text/plain"
                },
                "key": "Connection-Token",
                "value": "{{connectionToken}}"
              },
              {
                "key": "Accept",
                "value": "application/json"
              }
            ],
            "method": "GET"
          },
          "response": [],
          "event": [
            {
              "listen": "test",
              "script": {
                "id": "25256bb7-43bc-430f-9a3e-288bc4072cc7",
                "type": "text/javascript",
                "exec": [
                  "// Set response object as internal variable\nlet jsonData = {};\ntry {jsonData = pm.response.json();}catch(e){}\n",
                  "// Set property value as variable\nconst _resNext = jsonData?.next;\n",
                  "// pm.collectionVariables - Set nextCursor as variable for jsonData.next\nif (_resNext !== undefined) {\n   pm.collectionVariables.set(\"nextCursor\", jsonData.next);\n   console.log(\"- use {{nextCursor}} as collection variable for value\",jsonData.next);\n} else {\n   console.log('INFO - Unable to assign variable {{nextCursor}}, as jsonData.next is undefined.');\n};\n"
                ]
              }
            }
          ],
          "protocolProfileBehavior": {
            "disableBodyPruning": true
          }
        }
      ],
      "event": []
    },
    {
      "id": "f0c3f8fd-3549-46e5-a94f-e649a4f53afd",
      "name": "Vehicles",
      "description": {
        "content": "",
        "type": "text/plain"
      },
      "item": [
        {
          "id": "7f03af0e-a62b-4a8b-ac45-fea1b150a3a5",
          "name": "List Vehicles",
          "request": {
            "name": "List Vehicles",
            "description": {
              "content": "List all of the vehicles in the connected account",
              "type": "text/plain"
            },
            "url": {
              "path": [
                "vehicles"
              ],
              "host": [
                "{{baseUrl}}"
              ],
              "query": [
                {
                  "disabled": true,
                  "description": {
                    "content": "Pagination cursor to start requests from",
                    "type": "text/plain"
                  },
                  "key": "cursor",
                  "value": "{{nextCursor}}"
                },
                {
                  "disabled": true,
                  "description": {
                    "content": "The maximum number of results to return in a page.",
                    "type": "text/plain"
                  },
                  "key": "limit",
                  "value": "1"
                },
                {
                  "disabled": true,
                  "description": {
                    "content": "Only include records that were last modified after a provided date.",
                    "type": "text/plain"
                  },
                  "key": "modifiedAfter",
                  "value": "2021-01-06T03:24:53.000Z"
                },
                {
                  "disabled": true,
                  "description": {
                    "content": "Only include records that were last modified before a provided date.",
                    "type": "text/plain"
                  },
                  "key": "modifiedBefore",
                  "value": "2021-01-06T03:24:53.000Z"
                },
                {
                  "disabled": true,
                  "description": {
                    "content": "Include raw responses used to normalize model. Used for debugging or accessing unique properties that are not unified.",
                    "type": "text/plain"
                  },
                  "key": "raw",
                  "value": "true"
                },
                {
                  "disabled": true,
                  "description": {
                    "content": "Expand resources in the returned response",
                    "type": "text/plain"
                  },
                  "key": "expand",
                  "value": "vehicle"
                }
              ],
              "variable": []
            },
            "header": [
              {
                "disabled": false,
                "description": {
                  "content": "(Required) The token returned when a user authenticated their account. This authorizes access to a specific account.",
                  "type": "text/plain"
                },
                "key": "Connection-Token",
                "value": "{{connectionToken}}"
              },
              {
                "key": "Accept",
                "value": "application/json"
              }
            ],
            "method": "GET"
          },
          "response": [],
          "event": [
            {
              "listen": "test",
              "script": {
                "id": "fce5e850-416a-4b0b-8660-f730ac1acb33",
                "type": "text/javascript",
                "exec": [
                  "// Set response object as internal variable\nlet jsonData = {};\ntry {jsonData = pm.response.json();}catch(e){}\n",
                  "// Set property value as variable\nconst _resNext = jsonData?.next;\n",
                  "// pm.collectionVariables - Set nextCursor as variable for jsonData.next\nif (_resNext !== undefined) {\n   pm.collectionVariables.set(\"nextCursor\", jsonData.next);\n   console.log(\"- use {{nextCursor}} as collection variable for value\",jsonData.next);\n} else {\n   console.log('INFO - Unable to assign variable {{nextCursor}}, as jsonData.next is undefined.');\n};\n",
                  "// Set property value as variable\nconst _resResults0Id = jsonData?.results?.[0]?.id;\n",
                  "// pm.collectionVariables - Set vehicleId as variable for jsonData.results[0].id\nif (_resResults0Id !== undefined) {\n   pm.collectionVariables.set(\"vehicleId\", jsonData.results[0].id);\n   console.log(\"- use {{vehicleId}} as collection variable for value\",jsonData.results[0].id);\n} else {\n   console.log('INFO - Unable to assign variable {{vehicleId}}, as jsonData.results[0].id is undefined.');\n};\n"
                ]
              }
            }
          ],
          "protocolProfileBehavior": {
            "disableBodyPruning": true
          }
        },
        {
          "id": "95e9d1a0-97d5-4904-bd46-11292e9902f0",
          "name": "Get Vehicle",
          "request": {
            "name": "Get Vehicle",
            "description": {
              "content": "Get the details of a specific vehicle",
              "type": "text/plain"
            },
            "url": {
              "path": [
                "vehicles",
                ":id"
              ],
              "host": [
                "{{baseUrl}}"
              ],
              "query": [
                {
                  "disabled": true,
                  "description": {
                    "content": "Include raw responses used to normalize model. Used for debugging or accessing unique properties that are not unified.",
                    "type": "text/plain"
                  },
                  "key": "raw",
                  "value": "true"
                },
                {
                  "disabled": true,
                  "description": {
                    "content": "Expand resources in the returned response",
                    "type": "text/plain"
                  },
                  "key": "expand",
                  "value": "vehicle"
                }
              ],
              "variable": [
                {
                  "disabled": false,
                  "description": {
                    "content": "(Required) ",
                    "type": "text/plain"
                  },
                  "type": "string",
                  "value": "{{vehicleId}}",
                  "key": "id"
                }
              ]
            },
            "header": [
              {
                "disabled": false,
                "description": {
                  "content": "(Required) The token returned when a user authenticated their account. This authorizes access to a specific account.",
                  "type": "text/plain"
                },
                "key": "Connection-Token",
                "value": "{{connectionToken}}"
              },
              {
                "key": "Accept",
                "value": "application/json"
              }
            ],
            "method": "GET"
          },
          "response": [],
          "event": [
            {
              "listen": "test",
              "script": {
                "id": "f049abc4-1835-4c4d-bc09-3aacf885d92d",
                "type": "text/javascript",
                "exec": [
                  "// Set response object as internal variable\nlet jsonData = {};\ntry {jsonData = pm.response.json();}catch(e){}\n",
                  "// Set property value as variable\nconst _resNext = jsonData?.next;\n",
                  "// pm.collectionVariables - Set nextCursor as variable for jsonData.next\nif (_resNext !== undefined) {\n   pm.collectionVariables.set(\"nextCursor\", jsonData.next);\n   console.log(\"- use {{nextCursor}} as collection variable for value\",jsonData.next);\n} else {\n   console.log('INFO - Unable to assign variable {{nextCursor}}, as jsonData.next is undefined.');\n};\n"
                ]
              }
            }
          ],
          "protocolProfileBehavior": {
            "disableBodyPruning": true
          }
        },
        {
          "id": "d4a44de0-5beb-41ef-909b-c92689898d58",
          "name": "Latest Vehicle Locations",
          "request": {
            "name": "Latest Vehicle Locations",
            "description": {
              "content": "List the latest location of the vehicles in the connected account",
              "type": "text/plain"
            },
            "url": {
              "path": [
                "vehicles",
                "locations",
                ":id"
              ],
              "host": [
                "{{baseUrl}}"
              ],
              "query": [
                {
                  "disabled": true,
                  "description": {
                    "content": "Pagination cursor to start requests from",
                    "type": "text/plain"
                  },
                  "key": "cursor",
                  "value": "{{nextCursor}}"
                },
                {
                  "disabled": true,
                  "description": {
                    "content": "The maximum number of results to return in a page.",
                    "type": "text/plain"
                  },
                  "key": "limit",
                  "value": "1"
                },
                {
                  "disabled": true,
                  "description": {
                    "content": "Include raw responses used to normalize model. Used for debugging or accessing unique properties that are not unified.",
                    "type": "text/plain"
                  },
                  "key": "raw",
                  "value": "true"
                },
                {
                  "disabled": true,
                  "description": {
                    "content": "Expand resources in the returned response",
                    "type": "text/plain"
                  },
                  "key": "expand",
                  "value": "vehicle"
                }
              ],
              "variable": [
                {
                  "disabled": false,
                  "type": "any",
                  "value": "{{vehicleId}}",
                  "key": "id"
                }
              ]
            },
            "header": [
              {
                "disabled": false,
                "description": {
                  "content": "(Required) The token returned when a user authenticated their account. This authorizes access to a specific account.",
                  "type": "text/plain"
                },
                "key": "Connection-Token",
                "value": "{{connectionToken}}"
              },
              {
                "key": "Accept",
                "value": "application/json"
              }
            ],
            "method": "GET"
          },
          "response": [],
          "event": [
            {
              "listen": "test",
              "script": {
                "id": "20459945-1ac1-4158-8c62-b47b6ca0da1b",
                "type": "text/javascript",
                "exec": [
                  "// Set response object as internal variable\nlet jsonData = {};\ntry {jsonData = pm.response.json();}catch(e){}\n",
                  "// Set property value as variable\nconst _resNext = jsonData?.next;\n",
                  "// pm.collectionVariables - Set nextCursor as variable for jsonData.next\nif (_resNext !== undefined) {\n   pm.collectionVariables.set(\"nextCursor\", jsonData.next);\n   console.log(\"- use {{nextCursor}} as collection variable for value\",jsonData.next);\n} else {\n   console.log('INFO - Unable to assign variable {{nextCursor}}, as jsonData.next is undefined.');\n};\n"
                ]
              }
            }
          ],
          "protocolProfileBehavior": {
            "disableBodyPruning": true
          }
        },
        {
          "id": "d802ec16-ce38-436b-98c1-43d3f0c3caf7",
          "name": "Historical Vehicle Locations",
          "request": {
            "name": "Historical Vehicle Locations",
            "description": {
              "content": "List the historical breadcrumb locations for a vehicle.\n\n*Note:*\n\nGiven the large volume of location data available, we encourage customers to accept compressed (`gzip`) responses in order to maximize throughput. This is supported with many popular HTTP clients. Result limits vary depending on if results are compressed or not.",
              "type": "text/plain"
            },
            "url": {
              "path": [
                "vehicles",
                ":vehicleId",
                "locations"
              ],
              "host": [
                "{{baseUrl}}"
              ],
              "query": [
                {
                  "disabled": true,
                  "description": {
                    "content": "Pagination cursor to start requests from",
                    "type": "text/plain"
                  },
                  "key": "cursor",
                  "value": "{{nextCursor}}"
                },
                {
                  "disabled": true,
                  "description": {
                    "content": "The maximum number of results to return in a page.",
                    "type": "text/plain"
                  },
                  "key": "limit",
                  "value": "1"
                },
                {
                  "disabled": true,
                  "description": {
                    "content": "Timestamp to start from - defaults to `TODAY - 1 MONTH`",
                    "type": "text/plain"
                  },
                  "key": "startAt",
                  "value": "2021-01-06T03:24:53.000Z"
                },
                {
                  "disabled": true,
                  "description": {
                    "content": "Timestamp to end at - defaults to `TODAY`",
                    "type": "text/plain"
                  },
                  "key": "endAt",
                  "value": "2021-01-06T03:24:53.000Z"
                },
                {
                  "disabled": true,
                  "description": {
                    "content": "Include raw responses used to normalize model. Used for debugging or accessing unique properties that are not unified.",
                    "type": "text/plain"
                  },
                  "key": "raw",
                  "value": "true"
                }
              ],
              "variable": [
                {
                  "disabled": false,
                  "description": {
                    "content": "(Required) Vehicle to retrieve breadcrumb locations for",
                    "type": "text/plain"
                  },
                  "type": "string",
                  "value": "{{vehicleId}}",
                  "key": "vehicleId"
                }
              ]
            },
            "header": [
              {
                "disabled": false,
                "description": {
                  "content": "(Required) The token returned when a user authenticated their account. This authorizes access to a specific account.",
                  "type": "text/plain"
                },
                "key": "Connection-Token",
                "value": "{{connectionToken}}"
              },
              {
                "key": "Accept",
                "value": "application/json"
              }
            ],
            "method": "GET"
          },
          "response": [],
          "event": [
            {
              "listen": "test",
              "script": {
                "id": "d64e97d1-c895-4f37-b7b0-31c3a911487e",
                "type": "text/javascript",
                "exec": [
                  "// Set response object as internal variable\nlet jsonData = {};\ntry {jsonData = pm.response.json();}catch(e){}\n",
                  "// Set property value as variable\nconst _resNext = jsonData?.next;\n",
                  "// pm.collectionVariables - Set nextCursor as variable for jsonData.next\nif (_resNext !== undefined) {\n   pm.collectionVariables.set(\"nextCursor\", jsonData.next);\n   console.log(\"- use {{nextCursor}} as collection variable for value\",jsonData.next);\n} else {\n   console.log('INFO - Unable to assign variable {{nextCursor}}, as jsonData.next is undefined.');\n};\n"
                ]
              }
            }
          ],
          "protocolProfileBehavior": {
            "disableBodyPruning": true
          }
        },
        {
          "id": "e42e025c-fb96-4285-9b51-71ae6c242868",
          "name": "Historical Vehicle Stats",
          "request": {
            "name": "Historical Vehicle Stats",
            "description": {
              "content": "List historical stats and logs about the vehicle.",
              "type": "text/plain"
            },
            "url": {
              "path": [
                "vehicles",
                ":vehicleId",
                "stats",
                "historical"
              ],
              "host": [
                "{{baseUrl}}"
              ],
              "query": [
                {
                  "disabled": true,
                  "description": {
                    "content": "Pagination cursor to start requests from",
                    "type": "text/plain"
                  },
                  "key": "cursor",
                  "value": "{{nextCursor}}"
                },
                {
                  "disabled": true,
                  "description": {
                    "content": "The maximum number of results to return in a page.",
                    "type": "text/plain"
                  },
                  "key": "limit",
                  "value": "1"
                },
                {
                  "disabled": true,
                  "description": {
                    "content": "Expand resources in the returned response",
                    "type": "text/plain"
                  },
                  "key": "expand",
                  "value": "vehicle"
                },
                {
                  "disabled": true,
                  "description": {
                    "content": "Timestamp to start from - defaults to `TODAY - 1 MONTH`",
                    "type": "text/plain"
                  },
                  "key": "startAt",
                  "value": "2021-01-06T03:24:53.000Z"
                },
                {
                  "disabled": true,
                  "description": {
                    "content": "Timestamp to end at - defaults to `TODAY`",
                    "type": "text/plain"
                  },
                  "key": "endAt",
                  "value": "2021-01-06T03:24:53.000Z"
                },
                {
                  "disabled": true,
                  "description": {
                    "content": "Comma separated list of vehicle stats to filter for",
                    "type": "text/plain"
                  },
                  "key": "types",
                  "value": "odometer,engine_state"
                },
                {
                  "disabled": true,
                  "description": {
                    "content": "Include raw responses used to normalize model. Used for debugging or accessing unique properties that are not unified.",
                    "type": "text/plain"
                  },
                  "key": "raw",
                  "value": "true"
                }
              ],
              "variable": [
                {
                  "disabled": false,
                  "description": {
                    "content": "(Required) ",
                    "type": "text/plain"
                  },
                  "type": "string",
                  "value": "{{vehicleId}}",
                  "key": "vehicleId"
                }
              ]
            },
            "header": [
              {
                "disabled": false,
                "description": {
                  "content": "(Required) The token returned when a user authenticated their account. This authorizes access to a specific account.",
                  "type": "text/plain"
                },
                "key": "Connection-Token",
                "value": "{{connectionToken}}"
              },
              {
                "key": "Accept",
                "value": "application/json"
              }
            ],
            "method": "GET"
          },
          "response": [],
          "event": [
            {
              "listen": "test",
              "script": {
                "id": "f0dd6399-b5da-443c-9dd1-72a304a5d581",
                "type": "text/javascript",
                "exec": [
                  "// Set response object as internal variable\nlet jsonData = {};\ntry {jsonData = pm.response.json();}catch(e){}\n",
                  "// Set property value as variable\nconst _resNext = jsonData?.next;\n",
                  "// pm.collectionVariables - Set nextCursor as variable for jsonData.next\nif (_resNext !== undefined) {\n   pm.collectionVariables.set(\"nextCursor\", jsonData.next);\n   console.log(\"- use {{nextCursor}} as collection variable for value\",jsonData.next);\n} else {\n   console.log('INFO - Unable to assign variable {{nextCursor}}, as jsonData.next is undefined.');\n};\n"
                ]
              }
            }
          ],
          "protocolProfileBehavior": {
            "disableBodyPruning": true
          }
        }
      ],
      "event": []
    },
    {
      "id": "8afd2988-7b41-4d5d-b2c5-9ea1dbc63e2d",
      "name": "Webhook Events",
      "description": {
        "content": "",
        "type": "text/plain"
      },
      "item": [],
      "event": []
    }
  ],
  "auth": {
    "type": "bearer",
    "bearer": [
      {
        "type": "any",
        "value": "{{secretKey}}",
        "key": "token"
      }
    ]
  },
  "event": [],
  "variable": [
    {
      "type": "string",
      "value": "https://api.sandbox.withterminal.com/tsp/v1/",
      "key": "baseUrl"
    }
  ],
  "info": {
    "_postman_id": "963c901a-ab96-4cd0-a116-98252aeb3383",
    "name": "Telematics API",
    "schema": "https://schema.getpostman.com/json/collection/v2.1.0/collection.json",
    "description": {
      "content": "Terminal is a unified API that makes it easy to integrate with the leading telematics service providers.\n\nContact Support:\n Name: Terminal\n Email: connect@withterminal.com",
      "type": "text/plain"
    }
  }
}